pycdn/__init__.py
pycdn/cli.py
pycdn/client/__init__.py
pycdn/client/core.py
pycdn/client/import_hook.py
pycdn/client/lazy_loader.py
pycdn/server/__init__.py
pycdn/server/core.py
pycdn/server/runtime.py
pycdn/utils/__init__.py
pycdn/utils/common.py
pycdn/utils/encryption.py
pycdn-1.1.7.dist-info/licenses/LICENSE
pycdn-1.1.7.dist-info/METADATA
pycdn-1.1.7.dist-info/WHEEL
pycdn-1.1.7.dist-info/entry_points.txt
pycdn-1.1.7.dist-info/top_level.txt
pycdn-1.1.7.dist-info/RECORD
