Metadata-Version: 2.4
Name: pycdn
Version: 1.1.7
Summary: Revolutionary Package CDN with Natural Import System - Stream Python packages instantly without local installation!
Home-page: https://github.com/harshalmore2268/pycdn
Author: Harshal More
Author-email: Harshal More <harshalmore2468@gmail.com>
License:                                  Apache License
Project-URL: Homepage, https://github.com/harshalmore2268/pycdn
Project-URL: Repository, https://github.com/harshalmore2268/pycdn
Project-URL: Issues, https://github.com/harshalmore2268/pycdn/issues
Project-URL: Documentation, https://github.com/harshalmore2268/pycdn#readme
Project-URL: Changelog, https://github.com/harshalmore2268/pycdn/blob/main/CHANGELOG.md
Keywords: cdn,package-management,lazy-loading,serverless,import-system,streaming,netflix-for-packages
Classifier: Development Status :: 4 - Beta
Classifier: Intended Audience :: Developers
Classifier: License :: OSI Approved :: Apache Software License
Classifier: Operating System :: OS Independent
Classifier: Programming Language :: Python :: 3
Classifier: Programming Language :: Python :: 3.8
Classifier: Programming Language :: Python :: 3.9
Classifier: Programming Language :: Python :: 3.10
Classifier: Programming Language :: Python :: 3.11
Classifier: Programming Language :: Python :: 3.12
Classifier: Topic :: Software Development :: Libraries :: Python Modules
Classifier: Topic :: Internet :: WWW/HTTP :: HTTP Servers
Classifier: Topic :: System :: Software Distribution
Classifier: Topic :: Software Development :: Build Tools
Classifier: Topic :: Utilities
Requires-Python: >=3.8
License-File: LICENSE
Requires-Dist: fastapi>=0.68.0
Requires-Dist: uvicorn[standard]>=0.15.0
Requires-Dist: requests>=2.25.1
Requires-Dist: pydantic>=1.8.0
Requires-Dist: websockets>=10.0
Requires-Dist: cryptography>=41.0.0
Requires-Dist: python-dotenv>=1.0.0
Provides-Extra: dev
Requires-Dist: pytest>=6.0.0; extra == "dev"
Requires-Dist: pytest-asyncio>=0.18.0; extra == "dev"
Requires-Dist: httpx>=0.23.0; extra == "dev"
Requires-Dist: black>=21.0.0; extra == "dev"
Requires-Dist: isort>=5.0.0; extra == "dev"
Requires-Dist: flake8>=3.9.0; extra == "dev"
Provides-Extra: server
Requires-Dist: gunicorn>=20.0.0; extra == "server"
Dynamic: author
Dynamic: home-page
Dynamic: license-file
Dynamic: requires-python
